jasper/__init__.py
jasper/__main__.py
jasper/main.py
jasper/agent/__init__.py
jasper/agent/entity_extractor.py
jasper/agent/executor.py
jasper/agent/planner.py
jasper/agent/reflector.py
jasper/agent/synthesizer.py
jasper/agent/validator.py
jasper/cli/__init__.py
jasper/cli/interface.py
jasper/cli/main.py
jasper/cli/render.py
jasper/core/__init__.py
jasper/core/config.py
jasper/core/controller.py
jasper/core/errors.py
jasper/core/llm.py
jasper/core/state.py
jasper/export/__init__.py
jasper/export/pdf.py
jasper/observability/__init__.py
jasper/observability/logger.py
jasper/styles/report_v1.css
jasper/templates/report.html.jinja
jasper/tools/__init__.py
jasper/tools/aplha_vantage.py
jasper/tools/exceptions.py
jasper/tools/financials.py
jasper/tools/providers/alpha_vantage.py
jasper/tools/providers/yfinance.py
jasper_finance-1.0.7.dist-info/licenses/LICENSE
jasper_finance-1.0.7.dist-info/METADATA
jasper_finance-1.0.7.dist-info/WHEEL
jasper_finance-1.0.7.dist-info/entry_points.txt
jasper_finance-1.0.7.dist-info/top_level.txt
jasper_finance-1.0.7.dist-info/RECORD
