Metadata-Version: 2.4
Name: jasper-finance
Version: 1.0.7
Summary: Terminal-native autonomous financial research agent with deterministic planning and validation gating.
Author-email: ApexYash <apex@example.com>
License: MIT
Project-URL: Homepage, https://github.com/ApexYash11/jasper
Project-URL: Issues, https://github.com/ApexYash11/jasper/issues
Project-URL: Repository, https://github.com/ApexYash11/jasper
Keywords: finance,agent,research,autonomous,cli
Classifier: Development Status :: 5 - Production/Stable
Classifier: Environment :: Console
Classifier: Intended Audience :: Financial and Insurance Industry
Classifier: License :: OSI Approved :: MIT License
Classifier: Programming Language :: Python :: 3.9
Classifier: Programming Language :: Python :: 3.10
Classifier: Programming Language :: Python :: 3.11
Classifier: Topic :: Office/Business :: Financial
Requires-Python: >=3.9
License-File: LICENSE
Requires-Dist: typer[all]==0.9.0
Requires-Dist: click<9.0.0,>=8.0.0
Requires-Dist: rich==13.0.0
Requires-Dist: pydantic>=2.0.0
Requires-Dist: langchain-core>=0.1.0
Requires-Dist: langchain-openai>=0.1.0
Requires-Dist: openai>=1.0.0
Requires-Dist: httpx>=0.24.0
Requires-Dist: python-dotenv>=1.0.0
Requires-Dist: yfinance>=0.2.0
Requires-Dist: jinja2>=3.1.0
Requires-Dist: weasyprint>=60.0
Requires-Dist: xhtml2pdf>=0.2.15
Requires-Dist: markdown-it-py>=3.0.0
Provides-Extra: dev
Requires-Dist: pytest>=7.0; extra == "dev"
Requires-Dist: pytest-cov>=4.0; extra == "dev"
Dynamic: license-file
